odoo/addons/sale_credit_note_reversal/README.rst
odoo/addons/sale_credit_note_reversal/__init__.py
odoo/addons/sale_credit_note_reversal/__manifest__.py
odoo/addons/sale_credit_note_reversal/i18n/it.po
odoo/addons/sale_credit_note_reversal/i18n/sale_credit_note_reversal.pot
odoo/addons/sale_credit_note_reversal/models/__init__.py
odoo/addons/sale_credit_note_reversal/models/account_move.py
odoo/addons/sale_credit_note_reversal/readme/CONTRIBUTORS.rst
odoo/addons/sale_credit_note_reversal/readme/DESCRIPTION.rst
odoo/addons/sale_credit_note_reversal/readme/ROADMAP.rst
odoo/addons/sale_credit_note_reversal/static/description/icon.png
odoo/addons/sale_credit_note_reversal/static/description/index.html
odoo/addons/sale_credit_note_reversal/tests/__init__.py
odoo/addons/sale_credit_note_reversal/tests/test_sale_credit_note_reversal.py
odoo/addons/sale_credit_note_reversal/views/account_move_views.xml
odoo_addon_sale_credit_note_reversal-16.0.1.0.0.3.dist-info/METADATA
odoo_addon_sale_credit_note_reversal-16.0.1.0.0.3.dist-info/WHEEL
odoo_addon_sale_credit_note_reversal-16.0.1.0.0.3.dist-info/top_level.txt
odoo_addon_sale_credit_note_reversal-16.0.1.0.0.3.dist-info/RECORD
